{"P2": {"labels": ["Game"], "postTitle": "[CS2] \u6025\u505ccfg", "postUrl": "post/%5BCS2%5D%20-ji-ting-cfg.html", "createdDate": "2024-06-29", "dateLabelColor": "#bc4c00"}, "P1": {"labels": ["good first issue"], "postTitle": "Hi", "postUrl": "post/Hi.html", "createdDate": "2024-06-29", "dateLabelColor": "#bc4c00"}, "labelColorDict": {"bug": "#d73a4a", "documentation": "#0075ca", "duplicate": "#cfd3d7", "enhancement": "#a2eeef", "Game": "#1B0242", "good first issue": "#7057ff", "help wanted": "#008672", "invalid": "#e4e669", "question": "#d876e3", "wontfix": "#ffffff"}}